setup.py
simple_db_migrate/__init__.py
simple_db_migrate/cli.py
simple_db_migrate/config.py
simple_db_migrate/helpers.py
simple_db_migrate/log.py
simple_db_migrate/main.py
simple_db_migrate/mssql.py
simple_db_migrate/mysql.py
simple_db_migrate/oracle.py
simple_db_migrate.egg-info/PKG-INFO
simple_db_migrate.egg-info/SOURCES.txt
simple_db_migrate.egg-info/dependency_links.txt
simple_db_migrate.egg-info/entry_points.txt
simple_db_migrate.egg-info/top_level.txt
simple_db_migrate/core/__init__.py
simple_db_migrate/core/exceptions.py
simple_db_migrate/db_migrate/__init__.py
simple_db_migrate/db_migrate/management/__init__.py
simple_db_migrate/db_migrate/management/commands/__init__.py
simple_db_migrate/db_migrate/management/commands/dbmigrate.py
tests/__init__.py
tests/cli_test.py
tests/config_test.py
tests/core_test.py
tests/django_command_test.py
tests/django_test_settings.py
tests/exceptions_test.py
tests/helpers_test.py
tests/log_test.py
tests/main_test.py
tests/mssql_test.py
tests/mysql_test.py
tests/oracle_test.py
tests/run_test.py
tests/apps/__init__.py
tests/apps/app1/__init__.py
tests/apps/app2/__init__.py
tests/apps/app3/__init__.py