Metadata-Version: 1.0
Name: simple-db-migrate
Version: 3.0.1
Summary: simple-db-migrate is a database versioning and migration tool inspired on Rails Migrations.
Home-page: http://guilhermechapiewski.github.com/simple-db-migrate/
Author: Guilherme Chapiewski
Author-email: guilherme.chapiewski@gmail.com
License: Apache License 2.0
Keywords: database migration tool mysql
Platform: UNKNOWN
